yaypp/__init__.py
yaypp/yaypp.py
yaypp-0.2.2.dist-info/METADATA
yaypp-0.2.2.dist-info/WHEEL
yaypp-0.2.2.dist-info/top_level.txt
yaypp-0.2.2.dist-info/RECORD
